MANIFEST.in
README.rst
setup.py
opengraph_py3/__init__.py
opengraph_py3/opengraph.py
opengraph_py3/test.py
opengraph_py3.egg-info/PKG-INFO
opengraph_py3.egg-info/SOURCES.txt
opengraph_py3.egg-info/dependency_links.txt
opengraph_py3.egg-info/entry_points.txt
opengraph_py3.egg-info/not-zip-safe
opengraph_py3.egg-info/requires.txt
opengraph_py3.egg-info/top_level.txt