Metadata-Version: 1.1
Name: opengraph-py3
Version: 0.71
Summary: A module to parse the Open Graph Protocol. Ported to Python3.6 using 2to3-3.6
Home-page: https://github.com/erikriver/opengraph
Author: Erik Rivera
Author-email: erik.river@gmail.com
License: MIT
Keywords: opengraph protocol facebook
Platform: UNKNOWN
Classifier: Development Status :: 3 - Alpha
Classifier: Intended Audience :: Developers
Classifier: Programming Language :: Python
Classifier: Topic :: Text Processing :: Markup :: HTML
Classifier: Topic :: Software Development :: Libraries :: Python Modules
